AUTHORS
CHANGES.rst
LICENSE
MANIFEST.in
README.rst
auto_checklog.py
setup.py
nose_autochecklog.egg-info/PKG-INFO
nose_autochecklog.egg-info/SOURCES.txt
nose_autochecklog.egg-info/dependency_links.txt
nose_autochecklog.egg-info/entry_points.txt
nose_autochecklog.egg-info/requires.txt
nose_autochecklog.egg-info/top_level.txt
test/test_lesson1_autolog.py
test/test_lesson2_check.py