Metadata-Version: 1.1
Name: nose-autochecklog
Version: 0.1.1
Summary: nose plugin - auto check condition and log all checks
Home-page: https://github.com/steven004/nose-autochecklog
Author: Steven LI
Author-email: steven004@gmail.com
License: UNKNOWN
Keywords: nosetest logging assert
Platform: UNKNOWN
Classifier: Programming Language :: Python
Classifier: Development Status :: 4 - Beta
Classifier: Intended Audience :: Developers
Classifier: License :: OSI Approved :: MIT License
Classifier: Operating System :: OS Independent
Classifier: Topic :: System :: Logging
Classifier: Topic :: Software Development :: Testing
